<annotation>
	<folder>train_data</folder>
	<filename>DSC_0312.jpg</filename>
	<path>/home/guppy/Desktop/data/train_data/DSC_0312.jpg</path>
	<source>
		<database>Unknown</database>
	</source>
	<size>
		<width>3920</width>
		<height>2204</height>
		<depth>3</depth>
	</size>
	<segmented>0</segmented>
	<object>
		<name>speed_10</name>
		<pose>Unspecified</pose>
		<truncated>0</truncated>
		<difficult>0</difficult>
		<bndbox>
			<xmin>339</xmin>
			<ymin>491</ymin>
			<xmax>832</xmax>
			<ymax>953</ymax>
		</bndbox>
	</object>
	<object>
		<name>stop</name>
		<pose>Unspecified</pose>
		<truncated>0</truncated>
		<difficult>0</difficult>
		<bndbox>
			<xmin>720</xmin>
			<ymin>603</ymin>
			<xmax>1245</xmax>
			<ymax>1072</ymax>
		</bndbox>
	</object>
	<object>
		<name>speed_20</name>
		<pose>Unspecified</pose>
		<truncated>0</truncated>
		<difficult>0</difficult>
		<bndbox>
			<xmin>1153</xmin>
			<ymin>459</ymin>
			<xmax>1591</xmax>
			<ymax>897</ymax>
		</bndbox>
	</object>
	<object>
		<name>stop</name>
		<pose>Unspecified</pose>
		<truncated>0</truncated>
		<difficult>0</difficult>
		<bndbox>
			<xmin>1766</xmin>
			<ymin>522</ymin>
			<xmax>2234</xmax>
			<ymax>903</ymax>
		</bndbox>
	</object>
	<object>
		<name>speed_20</name>
		<pose>Unspecified</pose>
		<truncated>0</truncated>
		<difficult>0</difficult>
		<bndbox>
			<xmin>2109</xmin>
			<ymin>547</ymin>
			<xmax>2647</xmax>
			<ymax>1091</ymax>
		</bndbox>
	</object>
	<object>
		<name>speed_30</name>
		<pose>Unspecified</pose>
		<truncated>0</truncated>
		<difficult>0</difficult>
		<bndbox>
			<xmin>2580</xmin>
			<ymin>441</ymin>
			<xmax>3024</xmax>
			<ymax>897</ymax>
		</bndbox>
	</object>
</annotation>
